[
  {
    "id": "alert_1754238647091_wz3waaqsm",
    "timestamp": "2025-08-03T16:30:47.091Z",
    "acknowledged": false,
    "symbol": "OMF",
    "type": "insider",
    "severity": "high",
    "title": "Significant Insider BUY - OMF",
    "message": "Jane Doe (CFO) buy 11,231 shares for $5,090,805.184",
    "data": {
      "symbol": "OMF",
      "insider": "Jane Doe",
      "title": "CFO",
      "transactionType": "buy",
      "shares": 11231,
      "price": 453.2815585702778,
      "value": 5090805.18430279,
      "date": "2025-07-29T04:50:07.465Z",
      "filingDate": "2025-08-02T04:55:24.532Z",
      "ownershipPercent": 4.222031566518746
    }
  },
  {
    "id": "alert_1754238647092_ba5l0dws4",
    "timestamp": "2025-08-03T16:30:47.092Z",
    "acknowledged": false,
    "symbol": "OMF",
    "type": "insider",
    "severity": "high",
    "title": "Significant Insider BUY - OMF",
    "message": "Mike Johnson (CTO) buy 32,853 shares for $15,400,386.97",
    "data": {
      "symbol": "OMF",
      "insider": "Mike Johnson",
      "title": "CTO",
      "transactionType": "buy",
      "shares": 32853,
      "price": 468.76653485722477,
      "value": 15400386.969664406,
      "date": "2025-07-28T18:41:40.263Z",
      "filingDate": "2025-08-02T05:02:56.139Z",
      "ownershipPercent": 3.5892011169633906
    }
  },
  {
    "id": "alert_1754238647302_442r4dwal",
    "timestamp": "2025-08-03T16:30:47.302Z",
    "acknowledged": false,
    "symbol": "RL",
    "type": "insider",
    "severity": "high",
    "title": "Significant Insider BUY - RL",
    "message": "Mike Johnson (CTO) buy 42,914 shares for $19,645,091.767",
    "data": {
      "symbol": "RL",
      "insider": "Mike Johnson",
      "title": "CTO",
      "transactionType": "buy",
      "shares": 42914,
      "price": 457.77815554285473,
      "value": 19645091.766966067,
      "date": "2025-07-28T04:16:50.687Z",
      "filingDate": "2025-07-31T22:07:34.054Z",
      "ownershipPercent": 3.5021000102386304
    }
  },
  {
    "id": "alert_1754238647503_o0mvzt0n0",
    "timestamp": "2025-08-03T16:30:47.503Z",
    "acknowledged": false,
    "symbol": "STT",
    "type": "dark_pool",
    "severity": "medium",
    "title": "High Dark Pool Activity - STT",
    "message": "Dark pool volume represents 46.7% of total volume",
    "data": {
      "symbol": "STT",
      "date": "2025-08-03",
      "darkPoolVolume": 4851977,
      "totalVolume": 10393805,
      "darkPoolRatio": 0.46681431872158463,
      "avgDarkPoolSize": 7416,
      "sentiment": "neutral",
      "significantTrades": [
        {
          "size": 88608,
          "price": 455.148363222067,
          "timestamp": "2025-08-03T13:37:33.761Z"
        },
        {
          "size": 64471,
          "price": 454.10509547559633,
          "timestamp": "2025-08-03T15:16:19.718Z"
        },
        {
          "size": 88793,
          "price": 450.85227521075717,
          "timestamp": "2025-08-03T16:14:16.260Z"
        },
        {
          "size": 54087,
          "price": 450.91848566511777,
          "timestamp": "2025-08-03T12:47:04.234Z"
        },
        {
          "size": 109866,
          "price": 451.67558344234754,
          "timestamp": "2025-08-03T08:39:26.067Z"
        },
        {
          "size": 74888,
          "price": 456.06350924078697,
          "timestamp": "2025-08-03T10:18:49.834Z"
        }
      ]
    }
  },
  {
    "id": "alert_1754238647506_64dwai91p",
    "timestamp": "2025-08-03T16:30:47.506Z",
    "acknowledged": false,
    "symbol": "STT",
    "type": "insider",
    "severity": "medium",
    "title": "Significant Insider BUY - STT",
    "message": "John Smith (CEO) buy 2,237 shares for $1,039,662.866",
    "data": {
      "symbol": "STT",
      "insider": "John Smith",
      "title": "CEO",
      "transactionType": "buy",
      "shares": 2237,
      "price": 464.7576513949006,
      "value": 1039662.8661703927,
      "date": "2025-08-01T05:43:54.043Z",
      "filingDate": "2025-07-31T18:57:30.085Z",
      "ownershipPercent": 1.9820362130674496
    }
  },
  {
    "id": "alert_1754238647508_k6xmcwd2h",
    "timestamp": "2025-08-03T16:30:47.508Z",
    "acknowledged": false,
    "symbol": "STT",
    "type": "insider",
    "severity": "high",
    "title": "Significant Insider BUY - STT",
    "message": "John Smith (CEO) buy 41,980 shares for $19,773,223.971",
    "data": {
      "symbol": "STT",
      "insider": "John Smith",
      "title": "CEO",
      "transactionType": "buy",
      "shares": 41980,
      "price": 471.0153399423968,
      "value": 19773223.970781818,
      "date": "2025-07-31T12:07:51.385Z",
      "filingDate": "2025-08-02T20:40:45.994Z",
      "ownershipPercent": 0.9857715868418991
    }
  },
  {
    "id": "alert_1754238647509_zg554pjlt",
    "timestamp": "2025-08-03T16:30:47.509Z",
    "acknowledged": false,
    "symbol": "STT",
    "type": "insider",
    "severity": "high",
    "title": "Significant Insider SELL - STT",
    "message": "John Smith (CEO) sell 21,143 shares for $9,718,706.472",
    "data": {
      "symbol": "STT",
      "insider": "John Smith",
      "title": "CEO",
      "transactionType": "sell",
      "shares": 21143,
      "price": 459.66544348587746,
      "value": 9718706.471621906,
      "date": "2025-07-31T22:46:46.344Z",
      "filingDate": "2025-08-01T08:19:04.402Z",
      "ownershipPercent": 4.859546705357142
    }
  },
  {
    "id": "alert_1754238647722_g9r9qj8vf",
    "timestamp": "2025-08-03T16:30:47.722Z",
    "acknowledged": false,
    "symbol": "WCC",
    "type": "analyst",
    "severity": "medium",
    "title": "Analyst DOWNGRADE - WCC",
    "message": "Bank of America downgrades WCC to Sell with $437 target",
    "data": {
      "symbol": "WCC",
      "firm": "Bank of America",
      "analyst": "Research Team",
      "action": "downgrade",
      "previousRating": "Buy",
      "newRating": "Sell",
      "previousTarget": 469.12680180334445,
      "newTarget": 437.2197197022471,
      "date": "2025-07-30T21:45:11.226Z",
      "reasoning": "Margin pressure concerns"
    }
  },
  {
    "id": "alert_1754238647726_g5o7jja97",
    "timestamp": "2025-08-03T16:30:47.726Z",
    "acknowledged": false,
    "symbol": "WCC",
    "type": "insider",
    "severity": "medium",
    "title": "Significant Insider BUY - WCC",
    "message": "Sarah Wilson (Director) buy 5,311 shares for $2,415,751.053",
    "data": {
      "symbol": "WCC",
      "insider": "Sarah Wilson",
      "title": "Director",
      "transactionType": "buy",
      "shares": 5311,
      "price": 454.8580404475894,
      "value": 2415751.052817147,
      "date": "2025-07-29T12:37:54.576Z",
      "filingDate": "2025-08-01T22:54:04.919Z",
      "ownershipPercent": 3.1300144573497026
    }
  },
  {
    "id": "alert_1754238647727_cfr4jpf5o",
    "timestamp": "2025-08-03T16:30:47.727Z",
    "acknowledged": false,
    "symbol": "WCC",
    "type": "insider",
    "severity": "high",
    "title": "Significant Insider BUY - WCC",
    "message": "Sarah Wilson (Director) buy 39,584 shares for $18,359,462.526",
    "data": {
      "symbol": "WCC",
      "insider": "Sarah Wilson",
      "title": "Director",
      "transactionType": "buy",
      "shares": 39584,
      "price": 463.81018911453725,
      "value": 18359462.52590984,
      "date": "2025-07-31T18:22:50.012Z",
      "filingDate": "2025-08-02T20:55:15.126Z",
      "ownershipPercent": 1.848770752441553
    }
  },
  {
    "id": "alert_1754238647728_excd6kxmj",
    "timestamp": "2025-08-03T16:30:47.728Z",
    "acknowledged": false,
    "symbol": "WCC",
    "type": "insider",
    "severity": "high",
    "title": "Significant Insider BUY - WCC",
    "message": "John Smith (CEO) buy 47,215 shares for $21,616,877.072",
    "data": {
      "symbol": "WCC",
      "insider": "John Smith",
      "title": "CEO",
      "transactionType": "buy",
      "shares": 47215,
      "price": 457.8391839852494,
      "value": 21616877.07186355,
      "date": "2025-08-02T23:59:00.935Z",
      "filingDate": "2025-08-03T12:35:25.048Z",
      "ownershipPercent": 4.132883557312205
    }
  },
  {
    "id": "alert_1754238647732_j85wp7o4o",
    "timestamp": "2025-08-03T16:30:47.732Z",
    "acknowledged": false,
    "symbol": "C",
    "type": "news",
    "severity": "high",
    "title": "Important News - C",
    "message": "C reports strong Q4 earnings, beats estimates",
    "data": {
      "symbol": "C",
      "headline": "C reports strong Q4 earnings, beats estimates",
      "summary": "Recent developments suggest positive momentum for C with strong market reception.",
      "source": "Yahoo Finance",
      "sentiment": 0.5957129949564799,
      "importance": "high",
      "category": "earnings",
      "publishedAt": "2025-08-03T15:53:51.761Z",
      "url": "https://example.com/news/c-1754238647732"
    }
  },
  {
    "id": "alert_1754238647937_8nw6mfbst",
    "timestamp": "2025-08-03T16:30:47.937Z",
    "acknowledged": false,
    "symbol": "C",
    "type": "dark_pool",
    "severity": "medium",
    "title": "High Dark Pool Activity - C",
    "message": "Dark pool volume represents 49.5% of total volume",
    "data": {
      "symbol": "C",
      "date": "2025-08-03",
      "darkPoolVolume": 5804441,
      "totalVolume": 11725441,
      "darkPoolRatio": 0.49502965389532044,
      "avgDarkPoolSize": 10379,
      "sentiment": "neutral",
      "significantTrades": [
        {
          "size": 62100,
          "price": 460.32373325265587,
          "timestamp": "2025-08-03T09:44:47.702Z"
        },
        {
          "size": 81184,
          "price": 454.7988957542239,
          "timestamp": "2025-08-03T14:58:13.722Z"
        },
        {
          "size": 89463,
          "price": 458.8884239210479,
          "timestamp": "2025-08-03T14:33:59.422Z"
        }
      ]
    }
  },
  {
    "id": "alert_1754238647941_6iwdw4kxw",
    "timestamp": "2025-08-03T16:30:47.941Z",
    "acknowledged": false,
    "symbol": "C",
    "type": "insider",
    "severity": "high",
    "title": "Significant Insider BUY - C",
    "message": "Mike Johnson (CTO) buy 36,936 shares for $17,028,263.214",
    "data": {
      "symbol": "C",
      "insider": "Mike Johnson",
      "title": "CTO",
      "transactionType": "buy",
      "shares": 36936,
      "price": 461.02077142999644,
      "value": 17028263.21353835,
      "date": "2025-08-01T00:28:57.472Z",
      "filingDate": "2025-07-31T18:36:24.491Z",
      "ownershipPercent": 2.538050447455349
    }
  },
  {
    "id": "alert_1754238647943_b6wr1vk9a",
    "timestamp": "2025-08-03T16:30:47.943Z",
    "acknowledged": false,
    "symbol": "C",
    "type": "insider",
    "severity": "high",
    "title": "Significant Insider BUY - C",
    "message": "Mike Johnson (CTO) buy 27,754 shares for $12,980,062.812",
    "data": {
      "symbol": "C",
      "insider": "Mike Johnson",
      "title": "CTO",
      "transactionType": "buy",
      "shares": 27754,
      "price": 467.6825975227283,
      "value": 12980062.811645802,
      "date": "2025-08-02T13:01:15.546Z",
      "filingDate": "2025-08-03T11:03:46.127Z",
      "ownershipPercent": 4.26761573378905
    }
  },
  {
    "id": "alert_1754238647945_9xou0tz8g",
    "timestamp": "2025-08-03T16:30:47.945Z",
    "acknowledged": false,
    "symbol": "C",
    "type": "analyst",
    "severity": "medium",
    "title": "Analyst DOWNGRADE - C",
    "message": "Morgan Stanley downgrades C to Underperform with $475 target",
    "data": {
      "symbol": "C",
      "firm": "Morgan Stanley",
      "analyst": "Research Team",
      "action": "downgrade",
      "previousRating": "Outperform",
      "newRating": "Underperform",
      "previousTarget": 481.4380321939972,
      "newTarget": 474.56785755213764,
      "date": "2025-08-01T05:19:59.540Z",
      "reasoning": "Valuation concerns"
    }
  },
  {
    "id": "alert_1754238647946_t5swk6qwa",
    "timestamp": "2025-08-03T16:30:47.947Z",
    "acknowledged": false,
    "symbol": "C",
    "type": "analyst",
    "severity": "medium",
    "title": "Analyst DOWNGRADE - C",
    "message": "Wells Fargo downgrades C to Hold with $514 target",
    "data": {
      "symbol": "C",
      "firm": "Wells Fargo",
      "analyst": "Research Team",
      "action": "downgrade",
      "previousRating": "Hold",
      "newRating": "Hold",
      "previousTarget": 469.07318012192593,
      "newTarget": 514.2964251887172,
      "date": "2025-07-30T19:28:52.920Z",
      "reasoning": "Margin pressure concerns"
    }
  },
  {
    "id": "alert_1754238647954_8f2i20dtm",
    "timestamp": "2025-08-03T16:30:47.954Z",
    "acknowledged": false,
    "symbol": "CCEP",
    "type": "news",
    "severity": "high",
    "title": "Important News - CCEP",
    "message": "CCEP reports strong Q4 earnings, beats estimates",
    "data": {
      "symbol": "CCEP",
      "headline": "CCEP reports strong Q4 earnings, beats estimates",
      "summary": "Recent developments suggest positive momentum for CCEP with strong market reception.",
      "source": "Reuters",
      "sentiment": 0.8233155614091116,
      "importance": "high",
      "category": "earnings",
      "publishedAt": "2025-08-03T08:00:10.932Z",
      "url": "https://example.com/news/ccep-1754238647954"
    }
  },
  {
    "id": "alert_1754238648164_ynb1v1qfh",
    "timestamp": "2025-08-03T16:30:48.164Z",
    "acknowledged": false,
    "symbol": "CCEP",
    "type": "insider",
    "severity": "high",
    "title": "Significant Insider BUY - CCEP",
    "message": "John Smith (CEO) buy 29,430 shares for $13,007,952.993",
    "data": {
      "symbol": "CCEP",
      "insider": "John Smith",
      "title": "CEO",
      "transactionType": "buy",
      "shares": 29430,
      "price": 441.996364017224,
      "value": 13007952.993026901,
      "date": "2025-08-01T00:17:21.478Z",
      "filingDate": "2025-08-03T06:57:06.554Z",
      "ownershipPercent": 4.606364852671474
    }
  },
  {
    "id": "alert_1754238648166_ohdutodw5",
    "timestamp": "2025-08-03T16:30:48.166Z",
    "acknowledged": false,
    "symbol": "CCEP",
    "type": "insider",
    "severity": "high",
    "title": "Significant Insider SELL - CCEP",
    "message": "Jane Doe (CFO) sell 22,342 shares for $9,919,951.327",
    "data": {
      "symbol": "CCEP",
      "insider": "Jane Doe",
      "title": "CFO",
      "transactionType": "sell",
      "shares": 22342,
      "price": 444.00462478784436,
      "value": 9919951.327010019,
      "date": "2025-07-30T17:21:20.698Z",
      "filingDate": "2025-08-03T00:02:05.622Z",
      "ownershipPercent": 4.819415865617141
    }
  },
  {
    "id": "alert_1754238648169_qv1dfhxd7",
    "timestamp": "2025-08-03T16:30:48.169Z",
    "acknowledged": false,
    "symbol": "CCEP",
    "type": "analyst",
    "severity": "medium",
    "title": "Analyst UPGRADE - CCEP",
    "message": "Goldman Sachs upgrades CCEP to Underperform with $458 target",
    "data": {
      "symbol": "CCEP",
      "firm": "Goldman Sachs",
      "analyst": "Research Team",
      "action": "upgrade",
      "previousRating": "Outperform",
      "newRating": "Underperform",
      "previousTarget": 459.84340622981335,
      "newTarget": 458.49561901560844,
      "date": "2025-07-31T13:37:50.537Z",
      "reasoning": "Strong earnings momentum"
    }
  },
  {
    "id": "alert_1754238648170_ahpsesrzh",
    "timestamp": "2025-08-03T16:30:48.170Z",
    "acknowledged": false,
    "symbol": "CCEP",
    "type": "analyst",
    "severity": "medium",
    "title": "Analyst UPGRADE - CCEP",
    "message": "Bank of America upgrades CCEP to Underperform with $459 target",
    "data": {
      "symbol": "CCEP",
      "firm": "Bank of America",
      "analyst": "Research Team",
      "action": "upgrade",
      "previousRating": "Sell",
      "newRating": "Underperform",
      "previousTarget": 456.2336767908356,
      "newTarget": 459.0789847131025,
      "date": "2025-08-02T23:36:52.263Z",
      "reasoning": "Strong earnings momentum"
    }
  },
  {
    "id": "alert_1754238648173_zq64rfxsl",
    "timestamp": "2025-08-03T16:30:48.173Z",
    "acknowledged": false,
    "symbol": "CIB",
    "type": "news",
    "severity": "high",
    "title": "Important News - CIB",
    "message": "CIB raises full-year guidance",
    "data": {
      "symbol": "CIB",
      "headline": "CIB raises full-year guidance",
      "summary": "Recent developments suggest positive momentum for CIB with strong market reception.",
      "source": "MarketWatch",
      "sentiment": 0.6462749290391347,
      "importance": "high",
      "category": "guidance",
      "publishedAt": "2025-08-03T13:17:33.894Z",
      "url": "https://example.com/news/cib-1754238648173"
    }
  },
  {
    "id": "alert_1754238648379_sps2p80rj",
    "timestamp": "2025-08-03T16:30:48.379Z",
    "acknowledged": false,
    "symbol": "CIB",
    "type": "insider",
    "severity": "high",
    "title": "Significant Insider BUY - CIB",
    "message": "Sarah Wilson (Director) buy 47,890 shares for $22,412,976.681",
    "data": {
      "symbol": "CIB",
      "insider": "Sarah Wilson",
      "title": "Director",
      "transactionType": "buy",
      "shares": 47890,
      "price": 468.0095360353984,
      "value": 22412976.68073523,
      "date": "2025-07-30T10:25:47.147Z",
      "filingDate": "2025-08-02T20:55:03.900Z",
      "ownershipPercent": 2.2964267975213826
    }
  },
  {
    "id": "alert_1754238648382_0ipwa9eyl",
    "timestamp": "2025-08-03T16:30:48.382Z",
    "acknowledged": false,
    "symbol": "GL",
    "type": "news",
    "severity": "high",
    "title": "Important News - GL",
    "message": "GL reports strong Q4 earnings, beats estimates",
    "data": {
      "symbol": "GL",
      "headline": "GL reports strong Q4 earnings, beats estimates",
      "summary": "Recent developments suggest positive momentum for GL with strong market reception.",
      "source": "Bloomberg",
      "sentiment": 0.613132220932669,
      "importance": "high",
      "category": "earnings",
      "publishedAt": "2025-08-03T06:25:03.320Z",
      "url": "https://example.com/news/gl-1754238648382"
    }
  },
  {
    "id": "alert_1754238648383_orc8olqjr",
    "timestamp": "2025-08-03T16:30:48.383Z",
    "acknowledged": false,
    "symbol": "GL",
    "type": "news",
    "severity": "high",
    "title": "Important News - GL",
    "message": "GL raises full-year guidance",
    "data": {
      "symbol": "GL",
      "headline": "GL raises full-year guidance",
      "summary": "Recent developments suggest positive momentum for GL with strong market reception.",
      "source": "MarketWatch",
      "sentiment": 0.6367233157278993,
      "importance": "high",
      "category": "guidance",
      "publishedAt": "2025-08-03T13:05:23.149Z",
      "url": "https://example.com/news/gl-1754238648383"
    }
  },
  {
    "id": "alert_1754238648586_kknu1w1hh",
    "timestamp": "2025-08-03T16:30:48.586Z",
    "acknowledged": false,
    "symbol": "GL",
    "type": "analyst",
    "severity": "medium",
    "title": "Analyst DOWNGRADE - GL",
    "message": "JPMorgan downgrades GL to Hold with $510 target",
    "data": {
      "symbol": "GL",
      "firm": "JPMorgan",
      "analyst": "Research Team",
      "action": "downgrade",
      "previousRating": "Outperform",
      "newRating": "Hold",
      "previousTarget": 468.36471212451335,
      "newTarget": 510.4090438153412,
      "date": "2025-07-30T23:52:34.127Z",
      "reasoning": "Margin pressure concerns"
    }
  },
  {
    "id": "alert_1754238648587_vk776p7kt",
    "timestamp": "2025-08-03T16:30:48.587Z",
    "acknowledged": false,
    "symbol": "GL",
    "type": "analyst",
    "severity": "medium",
    "title": "Analyst DOWNGRADE - GL",
    "message": "Bank of America downgrades GL to Hold with $457 target",
    "data": {
      "symbol": "GL",
      "firm": "Bank of America",
      "analyst": "Research Team",
      "action": "downgrade",
      "previousRating": "Hold",
      "newRating": "Hold",
      "previousTarget": 488.9303762265415,
      "newTarget": 456.6233632149975,
      "date": "2025-08-03T16:16:58.747Z",
      "reasoning": "Margin pressure concerns"
    }
  },
  {
    "id": "alert_1754238648591_4doh01k5l",
    "timestamp": "2025-08-03T16:30:48.591Z",
    "acknowledged": false,
    "symbol": "GL",
    "type": "insider",
    "severity": "medium",
    "title": "Significant Insider BUY - GL",
    "message": "Sarah Wilson (Director) buy 6,124 shares for $2,728,363.074",
    "data": {
      "symbol": "GL",
      "insider": "Sarah Wilson",
      "title": "Director",
      "transactionType": "buy",
      "shares": 6124,
      "price": 445.5197704215674,
      "value": 2728363.0740616787,
      "date": "2025-08-03T13:49:16.979Z",
      "filingDate": "2025-08-01T10:52:00.100Z",
      "ownershipPercent": 1.1385248426686345
    }
  },
  {
    "id": "alert_1754238648803_9o9ke2kd8",
    "timestamp": "2025-08-03T16:30:48.803Z",
    "acknowledged": false,
    "symbol": "KB",
    "type": "insider",
    "severity": "medium",
    "title": "Significant Insider BUY - KB",
    "message": "Mike Johnson (CTO) buy 3,305 shares for $1,501,312.268",
    "data": {
      "symbol": "KB",
      "insider": "Mike Johnson",
      "title": "CTO",
      "transactionType": "buy",
      "shares": 3305,
      "price": 454.25484672440433,
      "value": 1501312.2684241564,
      "date": "2025-08-01T11:43:29.934Z",
      "filingDate": "2025-08-03T00:32:56.323Z",
      "ownershipPercent": 4.608913490943099
    }
  },
  {
    "id": "alert_1754238649008_wlsuadzda",
    "timestamp": "2025-08-03T16:30:49.008Z",
    "acknowledged": false,
    "symbol": "NIC",
    "type": "insider",
    "severity": "high",
    "title": "Significant Insider BUY - NIC",
    "message": "Jane Doe (CFO) buy 12,644 shares for $5,822,761.588",
    "data": {
      "symbol": "NIC",
      "insider": "Jane Doe",
      "title": "CFO",
      "transactionType": "buy",
      "shares": 12644,
      "price": 460.5157852318531,
      "value": 5822761.5884715505,
      "date": "2025-08-01T22:20:11.742Z",
      "filingDate": "2025-08-02T12:59:07.706Z",
      "ownershipPercent": 0.3112514792434494
    }
  },
  {
    "id": "alert_1754238649010_gzhrb1dxx",
    "timestamp": "2025-08-03T16:30:49.010Z",
    "acknowledged": false,
    "symbol": "NIC",
    "type": "insider",
    "severity": "high",
    "title": "Significant Insider SELL - NIC",
    "message": "Jane Doe (CFO) sell 16,319 shares for $7,392,206.705",
    "data": {
      "symbol": "NIC",
      "insider": "Jane Doe",
      "title": "CFO",
      "transactionType": "sell",
      "shares": 16319,
      "price": 452.98159846760063,
      "value": 7392206.705392775,
      "date": "2025-08-01T17:27:44.925Z",
      "filingDate": "2025-08-02T07:48:48.425Z",
      "ownershipPercent": 1.7496970679233181
    }
  },
  {
    "id": "alert_1754238649017_8gye591u2",
    "timestamp": "2025-08-03T16:30:49.017Z",
    "acknowledged": false,
    "symbol": "ROOT",
    "type": "news",
    "severity": "high",
    "title": "Important News - ROOT",
    "message": "ROOT raises full-year guidance",
    "data": {
      "symbol": "ROOT",
      "headline": "ROOT raises full-year guidance",
      "summary": "Recent developments suggest positive momentum for ROOT with strong market reception.",
      "source": "Yahoo Finance",
      "sentiment": 0.9633830736838052,
      "importance": "high",
      "category": "guidance",
      "publishedAt": "2025-08-03T13:31:17.171Z",
      "url": "https://example.com/news/root-1754238649017"
    }
  },
  {
    "id": "alert_1754238649219_wm2l233bb",
    "timestamp": "2025-08-03T16:30:49.219Z",
    "acknowledged": false,
    "symbol": "ROOT",
    "type": "insider",
    "severity": "medium",
    "title": "Significant Insider BUY - ROOT",
    "message": "Jane Doe (CFO) buy 2,817 shares for $1,300,573.891",
    "data": {
      "symbol": "ROOT",
      "insider": "Jane Doe",
      "title": "CFO",
      "transactionType": "buy",
      "shares": 2817,
      "price": 461.6875723938072,
      "value": 1300573.891433355,
      "date": "2025-08-02T00:23:12.679Z",
      "filingDate": "2025-08-01T12:51:12.348Z",
      "ownershipPercent": 1.2541287265951695
    }
  },
  {
    "id": "alert_1754238649220_q754ha82d",
    "timestamp": "2025-08-03T16:30:49.220Z",
    "acknowledged": false,
    "symbol": "ROOT",
    "type": "insider",
    "severity": "high",
    "title": "Significant Insider BUY - ROOT",
    "message": "Sarah Wilson (Director) buy 46,634 shares for $21,360,582.955",
    "data": {
      "symbol": "ROOT",
      "insider": "Sarah Wilson",
      "title": "Director",
      "transactionType": "buy",
      "shares": 46634,
      "price": 458.04741079524103,
      "value": 21360582.95502527,
      "date": "2025-07-28T08:08:35.138Z",
      "filingDate": "2025-08-02T22:03:08.702Z",
      "ownershipPercent": 3.6252983075252945
    }
  },
  {
    "id": "alert_1754238649221_qzitwelvx",
    "timestamp": "2025-08-03T16:30:49.221Z",
    "acknowledged": false,
    "symbol": "ROOT",
    "type": "insider",
    "severity": "high",
    "title": "Significant Insider BUY - ROOT",
    "message": "Sarah Wilson (Director) buy 34,537 shares for $15,262,932.064",
    "data": {
      "symbol": "ROOT",
      "insider": "Sarah Wilson",
      "title": "Director",
      "transactionType": "buy",
      "shares": 34537,
      "price": 441.92987416321444,
      "value": 15262932.063974937,
      "date": "2025-07-28T05:00:22.354Z",
      "filingDate": "2025-08-02T16:25:12.759Z",
      "ownershipPercent": 0.5448090111935732
    }
  },
  {
    "id": "alert_1754238649431_zjlu89m5i",
    "timestamp": "2025-08-03T16:30:49.431Z",
    "acknowledged": false,
    "symbol": "SYF",
    "type": "insider",
    "severity": "high",
    "title": "Significant Insider BUY - SYF",
    "message": "Sarah Wilson (Director) buy 28,677 shares for $13,177,955.148",
    "data": {
      "symbol": "SYF",
      "insider": "Sarah Wilson",
      "title": "Director",
      "transactionType": "buy",
      "shares": 28677,
      "price": 459.5304651039687,
      "value": 13177955.147786511,
      "date": "2025-07-31T11:01:32.709Z",
      "filingDate": "2025-08-02T19:54:01.328Z",
      "ownershipPercent": 1.420530466668074
    }
  },
  {
    "id": "alert_1754238649433_m0schjc2f",
    "timestamp": "2025-08-03T16:30:49.433Z",
    "acknowledged": false,
    "symbol": "SYF",
    "type": "insider",
    "severity": "high",
    "title": "Significant Insider SELL - SYF",
    "message": "Sarah Wilson (Director) sell 34,366 shares for $15,784,034.681",
    "data": {
      "symbol": "SYF",
      "insider": "Sarah Wilson",
      "title": "Director",
      "transactionType": "sell",
      "shares": 34366,
      "price": 459.2921690384567,
      "value": 15784034.681175603,
      "date": "2025-08-02T04:44:15.610Z",
      "filingDate": "2025-08-02T15:36:50.091Z",
      "ownershipPercent": 4.9548445632066205
    }
  },
  {
    "id": "alert_1754238649439_630d58pdf",
    "timestamp": "2025-08-03T16:30:49.439Z",
    "acknowledged": false,
    "symbol": "SYF",
    "type": "analyst",
    "severity": "medium",
    "title": "Analyst DOWNGRADE - SYF",
    "message": "Bank of America downgrades SYF to Underperform with $413 target",
    "data": {
      "symbol": "SYF",
      "firm": "Bank of America",
      "analyst": "Research Team",
      "action": "downgrade",
      "previousRating": "Outperform",
      "newRating": "Underperform",
      "previousTarget": 437.41460952196536,
      "newTarget": 413.21442321306586,
      "date": "2025-08-01T15:24:26.921Z",
      "reasoning": "Margin pressure concerns"
    }
  },
  {
    "id": "alert_1754238649645_dvxj9d6du",
    "timestamp": "2025-08-03T16:30:49.645Z",
    "acknowledged": false,
    "symbol": "FAST",
    "type": "analyst",
    "severity": "medium",
    "title": "Analyst UPGRADE - FAST",
    "message": "JPMorgan upgrades FAST to Underperform with $479 target",
    "data": {
      "symbol": "FAST",
      "firm": "JPMorgan",
      "analyst": "Research Team",
      "action": "upgrade",
      "previousRating": "Outperform",
      "newRating": "Underperform",
      "previousTarget": 518.8317047723534,
      "newTarget": 479.067558394274,
      "date": "2025-07-31T15:18:18.410Z",
      "reasoning": "Improved market position"
    }
  },
  {
    "id": "alert_1754238649648_l9o2335gi",
    "timestamp": "2025-08-03T16:30:49.648Z",
    "acknowledged": false,
    "symbol": "FAST",
    "type": "insider",
    "severity": "high",
    "title": "Significant Insider SELL - FAST",
    "message": "Sarah Wilson (Director) sell 45,795 shares for $20,656,082.053",
    "data": {
      "symbol": "FAST",
      "insider": "Sarah Wilson",
      "title": "Director",
      "transactionType": "sell",
      "shares": 45795,
      "price": 451.05540022418006,
      "value": 20656082.053266324,
      "date": "2025-08-02T22:09:00.619Z",
      "filingDate": "2025-08-02T06:11:20.241Z",
      "ownershipPercent": 2.6743138097328036
    }
  },
  {
    "id": "alert_1754238649851_v4f7nw8qi",
    "timestamp": "2025-08-03T16:30:49.851Z",
    "acknowledged": false,
    "symbol": "INDV",
    "type": "insider",
    "severity": "high",
    "title": "Significant Insider SELL - INDV",
    "message": "Sarah Wilson (Director) sell 28,082 shares for $12,623,498.305",
    "data": {
      "symbol": "INDV",
      "insider": "Sarah Wilson",
      "title": "Director",
      "transactionType": "sell",
      "shares": 28082,
      "price": 449.52276565846137,
      "value": 12623498.305220911,
      "date": "2025-07-31T22:06:12.769Z",
      "filingDate": "2025-08-02T09:53:39.100Z",
      "ownershipPercent": 1.2849577475331786
    }
  },
  {
    "id": "alert_1754238649852_t9h4501k7",
    "timestamp": "2025-08-03T16:30:49.852Z",
    "acknowledged": false,
    "symbol": "INDV",
    "type": "insider",
    "severity": "high",
    "title": "Significant Insider BUY - INDV",
    "message": "Sarah Wilson (Director) buy 40,555 shares for $18,881,161.387",
    "data": {
      "symbol": "INDV",
      "insider": "Sarah Wilson",
      "title": "Director",
      "transactionType": "buy",
      "shares": 40555,
      "price": 465.56926116818363,
      "value": 18881161.386675686,
      "date": "2025-07-29T21:42:55.456Z",
      "filingDate": "2025-08-03T13:43:37.267Z",
      "ownershipPercent": 4.5091085618967
    }
  },
  {
    "id": "alert_1754238649865_a67caxbdz",
    "timestamp": "2025-08-03T16:30:49.865Z",
    "acknowledged": false,
    "symbol": "ITRI",
    "type": "news",
    "severity": "high",
    "title": "Important News - ITRI",
    "message": "ITRI reports strong Q4 earnings, beats estimates",
    "data": {
      "symbol": "ITRI",
      "headline": "ITRI reports strong Q4 earnings, beats estimates",
      "summary": "Recent developments suggest positive momentum for ITRI with strong market reception.",
      "source": "Reuters",
      "sentiment": 0.8559557437136671,
      "importance": "high",
      "category": "earnings",
      "publishedAt": "2025-08-03T07:42:42.513Z",
      "url": "https://example.com/news/itri-1754238649865"
    }
  },
  {
    "id": "alert_1754238650073_vkxvxxz2t",
    "timestamp": "2025-08-03T16:30:50.073Z",
    "acknowledged": false,
    "symbol": "ITRI",
    "type": "analyst",
    "severity": "medium",
    "title": "Analyst DOWNGRADE - ITRI",
    "message": "Goldman Sachs downgrades ITRI to Buy with $420 target",
    "data": {
      "symbol": "ITRI",
      "firm": "Goldman Sachs",
      "analyst": "Research Team",
      "action": "downgrade",
      "previousRating": "Sell",
      "newRating": "Buy",
      "previousTarget": 449.69604607442454,
      "newTarget": 420.054351620275,
      "date": "2025-08-03T01:12:25.921Z",
      "reasoning": "Valuation concerns"
    }
  },
  {
    "id": "alert_1754238650076_8492yqkvg",
    "timestamp": "2025-08-03T16:30:50.076Z",
    "acknowledged": false,
    "symbol": "ITRI",
    "type": "insider",
    "severity": "high",
    "title": "Significant Insider BUY - ITRI",
    "message": "Jane Doe (CFO) buy 47,340 shares for $21,102,041.885",
    "data": {
      "symbol": "ITRI",
      "insider": "Jane Doe",
      "title": "CFO",
      "transactionType": "buy",
      "shares": 47340,
      "price": 445.7550039078586,
      "value": 21102041.884998027,
      "date": "2025-07-29T22:32:02.655Z",
      "filingDate": "2025-07-31T19:45:44.064Z",
      "ownershipPercent": 0.5352672760863807
    }
  },
  {
    "id": "alert_1754238650079_umj9wme3s",
    "timestamp": "2025-08-03T16:30:50.079Z",
    "acknowledged": false,
    "symbol": "JOYY",
    "type": "news",
    "severity": "high",
    "title": "Important News - JOYY",
    "message": "JOYY reports strong Q4 earnings, beats estimates",
    "data": {
      "symbol": "JOYY",
      "headline": "JOYY reports strong Q4 earnings, beats estimates",
      "summary": "Recent developments suggest positive momentum for JOYY with strong market reception.",
      "source": "Yahoo Finance",
      "sentiment": 0.7290119858907625,
      "importance": "high",
      "category": "earnings",
      "publishedAt": "2025-08-03T13:59:21.338Z",
      "url": "https://example.com/news/joyy-1754238650079"
    }
  },
  {
    "id": "alert_1754238650080_4wec1uxuq",
    "timestamp": "2025-08-03T16:30:50.080Z",
    "acknowledged": false,
    "symbol": "JOYY",
    "type": "news",
    "severity": "high",
    "title": "Important News - JOYY",
    "message": "JOYY raises full-year guidance",
    "data": {
      "symbol": "JOYY",
      "headline": "JOYY raises full-year guidance",
      "summary": "Recent developments suggest positive momentum for JOYY with strong market reception.",
      "source": "MarketWatch",
      "sentiment": 0.8548484803528597,
      "importance": "high",
      "category": "guidance",
      "publishedAt": "2025-08-03T10:10:37.643Z",
      "url": "https://example.com/news/joyy-1754238650080"
    }
  },
  {
    "id": "alert_1754238650288_9m76zo4h5",
    "timestamp": "2025-08-03T16:30:50.288Z",
    "acknowledged": false,
    "symbol": "JOYY",
    "type": "insider",
    "severity": "medium",
    "title": "Significant Insider BUY - JOYY",
    "message": "Jane Doe (CFO) buy 7,648 shares for $3,413,517.902",
    "data": {
      "symbol": "JOYY",
      "insider": "Jane Doe",
      "title": "CFO",
      "transactionType": "buy",
      "shares": 7648,
      "price": 446.3281775334606,
      "value": 3413517.9017759063,
      "date": "2025-07-29T04:18:05.207Z",
      "filingDate": "2025-08-01T14:12:31.979Z",
      "ownershipPercent": 1.4018329279739994
    }
  },
  {
    "id": "alert_1754238650293_kxhv20yiz",
    "timestamp": "2025-08-03T16:30:50.293Z",
    "acknowledged": false,
    "symbol": "JOYY",
    "type": "analyst",
    "severity": "medium",
    "title": "Analyst DOWNGRADE - JOYY",
    "message": "Wells Fargo downgrades JOYY to Hold with $423 target",
    "data": {
      "symbol": "JOYY",
      "firm": "Wells Fargo",
      "analyst": "Research Team",
      "action": "downgrade",
      "previousRating": "Hold",
      "newRating": "Hold",
      "previousTarget": 448.182174395419,
      "newTarget": 423.04559534554573,
      "date": "2025-07-31T21:18:14.331Z",
      "reasoning": "Valuation concerns"
    }
  },
  {
    "id": "alert_1754238650294_qu942netx",
    "timestamp": "2025-08-03T16:30:50.294Z",
    "acknowledged": false,
    "symbol": "JOYY",
    "type": "analyst",
    "severity": "medium",
    "title": "Analyst DOWNGRADE - JOYY",
    "message": "Wells Fargo downgrades JOYY to Underperform with $414 target",
    "data": {
      "symbol": "JOYY",
      "firm": "Wells Fargo",
      "analyst": "Research Team",
      "action": "downgrade",
      "previousRating": "Hold",
      "newRating": "Underperform",
      "previousTarget": 429.248678138669,
      "newTarget": 413.9868461270028,
      "date": "2025-08-01T10:51:15.759Z",
      "reasoning": "Competitive headwinds"
    }
  },
  {
    "id": "alert_1754238650493_8miyl5c62",
    "timestamp": "2025-08-03T16:30:50.493Z",
    "acknowledged": false,
    "symbol": "TNL",
    "type": "dark_pool",
    "severity": "high",
    "title": "High Dark Pool Activity - TNL",
    "message": "Dark pool volume represents 68.9% of total volume",
    "data": {
      "symbol": "TNL",
      "date": "2025-08-03",
      "darkPoolVolume": 5994424,
      "totalVolume": 8699894,
      "darkPoolRatio": 0.6890226478621464,
      "avgDarkPoolSize": 3749,
      "sentiment": "bullish",
      "significantTrades": [
        {
          "size": 69713,
          "price": 454.83273125597566,
          "timestamp": "2025-08-03T15:44:06.270Z"
        },
        {
          "size": 80296,
          "price": 449.7375225447355,
          "timestamp": "2025-08-03T12:53:56.839Z"
        },
        {
          "size": 113534,
          "price": 452.16517766020075,
          "timestamp": "2025-08-03T14:39:59.358Z"
        },
        {
          "size": 62143,
          "price": 449.99322778981195,
          "timestamp": "2025-08-03T09:24:43.135Z"
        },
        {
          "size": 69197,
          "price": 448.8577204955464,
          "timestamp": "2025-08-03T15:42:38.615Z"
        }
      ]
    }
  },
  {
    "id": "alert_1754238650497_riughv1be",
    "timestamp": "2025-08-03T16:30:50.497Z",
    "acknowledged": false,
    "symbol": "TNL",
    "type": "insider",
    "severity": "high",
    "title": "Significant Insider SELL - TNL",
    "message": "Sarah Wilson (Director) sell 45,259 shares for $20,583,821.556",
    "data": {
      "symbol": "TNL",
      "insider": "Sarah Wilson",
      "title": "Director",
      "transactionType": "sell",
      "shares": 45259,
      "price": 454.8006265197723,
      "value": 20583821.555658374,
      "date": "2025-07-30T15:22:21.816Z",
      "filingDate": "2025-08-02T08:01:53.406Z",
      "ownershipPercent": 0.3567505332740194
    }
  },
  {
    "id": "alert_1754238650498_zk6yncqbu",
    "timestamp": "2025-08-03T16:30:50.498Z",
    "acknowledged": false,
    "symbol": "TNL",
    "type": "insider",
    "severity": "high",
    "title": "Significant Insider SELL - TNL",
    "message": "John Smith (CEO) sell 37,357 shares for $17,184,026.998",
    "data": {
      "symbol": "TNL",
      "insider": "John Smith",
      "title": "CEO",
      "transactionType": "sell",
      "shares": 37357,
      "price": 459.9948335730923,
      "value": 17184026.99779001,
      "date": "2025-08-02T13:38:32.341Z",
      "filingDate": "2025-08-01T10:53:11.072Z",
      "ownershipPercent": 2.7364607006268824
    }
  },
  {
    "id": "alert_1754238650499_5jr87kt6u",
    "timestamp": "2025-08-03T16:30:50.499Z",
    "acknowledged": false,
    "symbol": "TNL",
    "type": "insider",
    "severity": "high",
    "title": "Significant Insider BUY - TNL",
    "message": "John Smith (CEO) buy 31,312 shares for $13,954,329.493",
    "data": {
      "symbol": "TNL",
      "insider": "John Smith",
      "title": "CEO",
      "transactionType": "buy",
      "shares": 31312,
      "price": 445.65436550339575,
      "value": 13954329.492642328,
      "date": "2025-07-28T04:51:55.335Z",
      "filingDate": "2025-08-02T21:10:37.060Z",
      "ownershipPercent": 2.471505984404613
    }
  },
  {
    "id": "alert_1754238650503_ws59t40ap",
    "timestamp": "2025-08-03T16:30:50.503Z",
    "acknowledged": false,
    "symbol": "TNL",
    "type": "analyst",
    "severity": "medium",
    "title": "Analyst UPGRADE - TNL",
    "message": "Goldman Sachs upgrades TNL to Buy with $380 target",
    "data": {
      "symbol": "TNL",
      "firm": "Goldman Sachs",
      "analyst": "Research Team",
      "action": "upgrade",
      "previousRating": "Hold",
      "newRating": "Buy",
      "previousTarget": 410.16619626226407,
      "newTarget": 380.4343299387918,
      "date": "2025-07-31T03:34:16.237Z",
      "reasoning": "Improved market position"
    }
  },
  {
    "id": "alert_1754238650707_arucuwoc8",
    "timestamp": "2025-08-03T16:30:50.707Z",
    "acknowledged": false,
    "symbol": "WFC",
    "type": "insider",
    "severity": "high",
    "title": "Significant Insider BUY - WFC",
    "message": "John Smith (CEO) buy 22,035 shares for $10,198,397.128",
    "data": {
      "symbol": "WFC",
      "insider": "John Smith",
      "title": "CEO",
      "transactionType": "buy",
      "shares": 22035,
      "price": 462.82718983031526,
      "value": 10198397.127910998,
      "date": "2025-08-01T19:46:36.412Z",
      "filingDate": "2025-08-03T03:15:37.360Z",
      "ownershipPercent": 4.102079758466987
    }
  },
  {
    "id": "alert_1754238650710_vheuavww2",
    "timestamp": "2025-08-03T16:30:50.710Z",
    "acknowledged": false,
    "symbol": "WFC",
    "type": "dark_pool",
    "severity": "medium",
    "title": "High Dark Pool Activity - WFC",
    "message": "Dark pool volume represents 51.4% of total volume",
    "data": {
      "symbol": "WFC",
      "date": "2025-08-03",
      "darkPoolVolume": 5586360,
      "totalVolume": 10873522,
      "darkPoolRatio": 0.513758099721507,
      "avgDarkPoolSize": 1039,
      "sentiment": "neutral",
      "significantTrades": [
        {
          "size": 56618,
          "price": 461.09403669369937,
          "timestamp": "2025-08-03T12:57:42.477Z"
        },
        {
          "size": 140211,
          "price": 455.27625739796116,
          "timestamp": "2025-08-03T09:20:21.886Z"
        },
        {
          "size": 51836,
          "price": 456.36887478326287,
          "timestamp": "2025-08-03T14:50:00.672Z"
        },
        {
          "size": 85602,
          "price": 458.58197323963475,
          "timestamp": "2025-08-03T12:38:13.856Z"
        }
      ]
    }
  },
  {
    "id": "alert_1754238650713_d0a26ckhs",
    "timestamp": "2025-08-03T16:30:50.713Z",
    "acknowledged": false,
    "symbol": "WFC",
    "type": "analyst",
    "severity": "medium",
    "title": "Analyst UPGRADE - WFC",
    "message": "Bank of America upgrades WFC to Buy with $404 target",
    "data": {
      "symbol": "WFC",
      "firm": "Bank of America",
      "analyst": "Research Team",
      "action": "upgrade",
      "previousRating": "Sell",
      "newRating": "Buy",
      "previousTarget": 431.45808615180374,
      "newTarget": 404.1543402129831,
      "date": "2025-08-03T13:14:53.139Z",
      "reasoning": "Strong earnings momentum"
    }
  },
  {
    "id": "alert_1754238650915_ymxanxa07",
    "timestamp": "2025-08-03T16:30:50.915Z",
    "acknowledged": false,
    "symbol": "WING",
    "type": "dark_pool",
    "severity": "high",
    "title": "High Dark Pool Activity - WING",
    "message": "Dark pool volume represents 77.1% of total volume",
    "data": {
      "symbol": "WING",
      "date": "2025-08-03",
      "darkPoolVolume": 5068635,
      "totalVolume": 6572466,
      "darkPoolRatio": 0.7711922739501429,
      "avgDarkPoolSize": 9893,
      "sentiment": "bullish",
      "significantTrades": [
        {
          "size": 121959,
          "price": 449.92196251222055,
          "timestamp": "2025-08-03T10:58:52.962Z"
        },
        {
          "size": 106106,
          "price": 450.65381382533633,
          "timestamp": "2025-08-03T13:50:34.884Z"
        },
        {
          "size": 66809,
          "price": 456.80314119934167,
          "timestamp": "2025-08-03T11:21:23.205Z"
        },
        {
          "size": 73559,
          "price": 458.3779254147126,
          "timestamp": "2025-08-03T08:47:57.071Z"
        }
      ]
    }
  },
  {
    "id": "alert_1754238650923_3lnt3kto1",
    "timestamp": "2025-08-03T16:30:50.923Z",
    "acknowledged": false,
    "symbol": "WING",
    "type": "analyst",
    "severity": "medium",
    "title": "Analyst DOWNGRADE - WING",
    "message": "Bank of America downgrades WING to Underperform with $372 target",
    "data": {
      "symbol": "WING",
      "firm": "Bank of America",
      "analyst": "Research Team",
      "action": "downgrade",
      "previousRating": "Outperform",
      "newRating": "Underperform",
      "previousTarget": 404.59579666729314,
      "newTarget": 371.6839100531955,
      "date": "2025-07-31T06:07:37.880Z",
      "reasoning": "Competitive headwinds"
    }
  },
  {
    "id": "alert_1754238650926_lt1744bt4",
    "timestamp": "2025-08-03T16:30:50.926Z",
    "acknowledged": false,
    "symbol": "WING",
    "type": "insider",
    "severity": "high",
    "title": "Significant Insider BUY - WING",
    "message": "Sarah Wilson (Director) buy 50,051 shares for $22,956,624.992",
    "data": {
      "symbol": "WING",
      "insider": "Sarah Wilson",
      "title": "Director",
      "transactionType": "buy",
      "shares": 50051,
      "price": 458.6646618802295,
      "value": 22956624.99176737,
      "date": "2025-07-28T21:46:09.867Z",
      "filingDate": "2025-08-03T05:54:39.620Z",
      "ownershipPercent": 3.638654604828876
    }
  },
  {
    "id": "alert_1754238650927_08rcjz8c1",
    "timestamp": "2025-08-03T16:30:50.927Z",
    "acknowledged": false,
    "symbol": "WING",
    "type": "insider",
    "severity": "high",
    "title": "Significant Insider SELL - WING",
    "message": "John Smith (CEO) sell 49,538 shares for $23,082,488.861",
    "data": {
      "symbol": "WING",
      "insider": "John Smith",
      "title": "CEO",
      "transactionType": "sell",
      "shares": 49538,
      "price": 465.9552033017077,
      "value": 23082488.861159995,
      "date": "2025-08-01T11:06:56.817Z",
      "filingDate": "2025-08-01T12:48:38.429Z",
      "ownershipPercent": 2.418217494129755
    }
  },
  {
    "id": "alert_1754238650930_mfb25dybg",
    "timestamp": "2025-08-03T16:30:50.930Z",
    "acknowledged": false,
    "symbol": "WTS",
    "type": "news",
    "severity": "high",
    "title": "Important News - WTS",
    "message": "WTS raises full-year guidance",
    "data": {
      "symbol": "WTS",
      "headline": "WTS raises full-year guidance",
      "summary": "Recent developments suggest positive momentum for WTS with strong market reception.",
      "source": "Reuters",
      "sentiment": 0.7561047791559202,
      "importance": "high",
      "category": "guidance",
      "publishedAt": "2025-08-03T09:42:06.289Z",
      "url": "https://example.com/news/wts-1754238650930"
    }
  },
  {
    "id": "alert_1754238651128_e2i331r90",
    "timestamp": "2025-08-03T16:30:51.128Z",
    "acknowledged": false,
    "symbol": "WTS",
    "type": "dark_pool",
    "severity": "medium",
    "title": "High Dark Pool Activity - WTS",
    "message": "Dark pool volume represents 49.6% of total volume",
    "data": {
      "symbol": "WTS",
      "date": "2025-08-03",
      "darkPoolVolume": 3033084,
      "totalVolume": 6112395,
      "darkPoolRatio": 0.4962185853499324,
      "avgDarkPoolSize": 9508,
      "sentiment": "bearish",
      "significantTrades": [
        {
          "size": 68339,
          "price": 462.1968418699115,
          "timestamp": "2025-08-03T15:31:04.143Z"
        },
        {
          "size": 114102,
          "price": 453.98226376887135,
          "timestamp": "2025-08-03T13:08:55.550Z"
        },
        {
          "size": 100635,
          "price": 456.4913439792459,
          "timestamp": "2025-08-03T14:16:14.121Z"
        },
        {
          "size": 123719,
          "price": 455.32676230333203,
          "timestamp": "2025-08-03T09:37:18.758Z"
        }
      ]
    }
  },
  {
    "id": "alert_1754238651133_60ncam87y",
    "timestamp": "2025-08-03T16:30:51.133Z",
    "acknowledged": false,
    "symbol": "WTS",
    "type": "insider",
    "severity": "high",
    "title": "Significant Insider BUY - WTS",
    "message": "Sarah Wilson (Director) buy 45,269 shares for $21,079,070.543",
    "data": {
      "symbol": "WTS",
      "insider": "Sarah Wilson",
      "title": "Director",
      "transactionType": "buy",
      "shares": 45269,
      "price": 465.64029563972707,
      "value": 21079070.543314803,
      "date": "2025-08-03T03:39:37.608Z",
      "filingDate": "2025-08-03T06:19:01.859Z",
      "ownershipPercent": 0.709410500365336
    }
  },
  {
    "id": "alert_1754238651136_kt7j5nvvb",
    "timestamp": "2025-08-03T16:30:51.136Z",
    "acknowledged": false,
    "symbol": "WTS",
    "type": "analyst",
    "severity": "medium",
    "title": "Analyst DOWNGRADE - WTS",
    "message": "Goldman Sachs downgrades WTS to Sell with $504 target",
    "data": {
      "symbol": "WTS",
      "firm": "Goldman Sachs",
      "analyst": "Research Team",
      "action": "downgrade",
      "previousRating": "Underperform",
      "newRating": "Sell",
      "previousTarget": 495.1038422006494,
      "newTarget": 503.6445464352832,
      "date": "2025-08-03T12:11:12.796Z",
      "reasoning": "Competitive headwinds"
    }
  },
  {
    "id": "alert_1754238651137_pvgwnbmf2",
    "timestamp": "2025-08-03T16:30:51.137Z",
    "acknowledged": false,
    "symbol": "WTS",
    "type": "analyst",
    "severity": "medium",
    "title": "Analyst UPGRADE - WTS",
    "message": "Barclays upgrades WTS to Hold with $372 target",
    "data": {
      "symbol": "WTS",
      "firm": "Barclays",
      "analyst": "Research Team",
      "action": "upgrade",
      "previousRating": "Hold",
      "newRating": "Hold",
      "previousTarget": 397.9096795107345,
      "newTarget": 372.26803603402556,
      "date": "2025-08-03T05:55:09.860Z",
      "reasoning": "Positive sector outlook"
    }
  },
  {
    "id": "alert_1754238651346_1mwuxph4u",
    "timestamp": "2025-08-03T16:30:51.346Z",
    "acknowledged": false,
    "symbol": "XYL",
    "type": "analyst",
    "severity": "medium",
    "title": "Analyst UPGRADE - XYL",
    "message": "Goldman Sachs upgrades XYL to Hold with $463 target",
    "data": {
      "symbol": "XYL",
      "firm": "Goldman Sachs",
      "analyst": "Research Team",
      "action": "upgrade",
      "previousRating": "Buy",
      "newRating": "Hold",
      "previousTarget": 487.3779522076302,
      "newTarget": 462.8840307133569,
      "date": "2025-08-02T22:14:17.289Z",
      "reasoning": "Strong earnings momentum"
    }
  },
  {
    "id": "alert_1754238651349_x3w93w6lf",
    "timestamp": "2025-08-03T16:30:51.349Z",
    "acknowledged": false,
    "symbol": "XYL",
    "type": "insider",
    "severity": "high",
    "title": "Significant Insider SELL - XYL",
    "message": "Sarah Wilson (Director) sell 50,240 shares for $23,221,199.341",
    "data": {
      "symbol": "XYL",
      "insider": "Sarah Wilson",
      "title": "Director",
      "transactionType": "sell",
      "shares": 50240,
      "price": 462.2054008996825,
      "value": 23221199.34120005,
      "date": "2025-07-28T05:49:14.013Z",
      "filingDate": "2025-08-02T06:00:04.855Z",
      "ownershipPercent": 4.936710930511548
    }
  },
  {
    "id": "alert_1754238651352_7jos0p07d",
    "timestamp": "2025-08-03T16:30:51.352Z",
    "acknowledged": false,
    "symbol": "AMG",
    "type": "news",
    "severity": "high",
    "title": "Important News - AMG",
    "message": "AMG raises full-year guidance",
    "data": {
      "symbol": "AMG",
      "headline": "AMG raises full-year guidance",
      "summary": "Recent developments suggest positive momentum for AMG with strong market reception.",
      "source": "CNBC",
      "sentiment": 0.8392729921472003,
      "importance": "high",
      "category": "guidance",
      "publishedAt": "2025-08-03T07:30:46.120Z",
      "url": "https://example.com/news/amg-1754238651352"
    }
  },
  {
    "id": "alert_1754238651353_rb4n3fss1",
    "timestamp": "2025-08-03T16:30:51.353Z",
    "acknowledged": false,
    "symbol": "AMG",
    "type": "news",
    "severity": "high",
    "title": "Important News - AMG",
    "message": "AMG reports strong Q4 earnings, beats estimates",
    "data": {
      "symbol": "AMG",
      "headline": "AMG reports strong Q4 earnings, beats estimates",
      "summary": "Recent developments suggest positive momentum for AMG with strong market reception.",
      "source": "CNBC",
      "sentiment": 0.6638547838332589,
      "importance": "high",
      "category": "earnings",
      "publishedAt": "2025-08-03T10:05:27.157Z",
      "url": "https://example.com/news/amg-1754238651353"
    }
  },
  {
    "id": "alert_1754238651562_qkqp03j7m",
    "timestamp": "2025-08-03T16:30:51.562Z",
    "acknowledged": false,
    "symbol": "AMG",
    "type": "analyst",
    "severity": "medium",
    "title": "Analyst DOWNGRADE - AMG",
    "message": "Goldman Sachs downgrades AMG to Hold with $387 target",
    "data": {
      "symbol": "AMG",
      "firm": "Goldman Sachs",
      "analyst": "Research Team",
      "action": "downgrade",
      "previousRating": "Sell",
      "newRating": "Hold",
      "previousTarget": 404.8707144568602,
      "newTarget": 386.66652089196083,
      "date": "2025-08-02T02:06:44.831Z",
      "reasoning": "Competitive headwinds"
    }
  },
  {
    "id": "alert_1754238651563_vidt5pu3q",
    "timestamp": "2025-08-03T16:30:51.563Z",
    "acknowledged": false,
    "symbol": "AMG",
    "type": "analyst",
    "severity": "medium",
    "title": "Analyst UPGRADE - AMG",
    "message": "Barclays upgrades AMG to Hold with $505 target",
    "data": {
      "symbol": "AMG",
      "firm": "Barclays",
      "analyst": "Research Team",
      "action": "upgrade",
      "previousRating": "Underperform",
      "newRating": "Hold",
      "previousTarget": 488.07630506038976,
      "newTarget": 504.7126080559435,
      "date": "2025-07-31T21:43:12.977Z",
      "reasoning": "Improved market position"
    }
  },
  {
    "id": "alert_1754238651566_fg6vuzrfg",
    "timestamp": "2025-08-03T16:30:51.566Z",
    "acknowledged": false,
    "symbol": "AMG",
    "type": "insider",
    "severity": "high",
    "title": "Significant Insider BUY - AMG",
    "message": "Mike Johnson (CTO) buy 36,702 shares for $16,557,860.867",
    "data": {
      "symbol": "AMG",
      "insider": "Mike Johnson",
      "title": "CTO",
      "transactionType": "buy",
      "shares": 36702,
      "price": 451.14328557930185,
      "value": 16557860.867331536,
      "date": "2025-07-30T00:23:47.562Z",
      "filingDate": "2025-08-02T21:27:07.787Z",
      "ownershipPercent": 2.0398436190368208
    }
  },
  {
    "id": "alert_1754238651567_o3fd8dwy8",
    "timestamp": "2025-08-03T16:30:51.567Z",
    "acknowledged": false,
    "symbol": "AMG",
    "type": "insider",
    "severity": "medium",
    "title": "Significant Insider BUY - AMG",
    "message": "Mike Johnson (CTO) buy 10,376 shares for $4,714,445.793",
    "data": {
      "symbol": "AMG",
      "insider": "Mike Johnson",
      "title": "CTO",
      "transactionType": "buy",
      "shares": 10376,
      "price": 454.360619966804,
      "value": 4714445.792775558,
      "date": "2025-07-29T14:46:50.054Z",
      "filingDate": "2025-08-02T12:40:36.917Z",
      "ownershipPercent": 3.7406725132467478
    }
  },
  {
    "id": "alert_1754238651568_uthvc0ofj",
    "timestamp": "2025-08-03T16:30:51.568Z",
    "acknowledged": false,
    "symbol": "AMG",
    "type": "insider",
    "severity": "high",
    "title": "Significant Insider BUY - AMG",
    "message": "John Smith (CEO) buy 23,224 shares for $10,530,434.364",
    "data": {
      "symbol": "AMG",
      "insider": "John Smith",
      "title": "CEO",
      "transactionType": "buy",
      "shares": 23224,
      "price": 453.42896849939376,
      "value": 10530434.36442992,
      "date": "2025-07-30T08:29:09.636Z",
      "filingDate": "2025-08-01T02:25:14.747Z",
      "ownershipPercent": 3.968269036284433
    }
  },
  {
    "id": "alert_1754238651571_cawa46wu3",
    "timestamp": "2025-08-03T16:30:51.571Z",
    "acknowledged": false,
    "symbol": "FTI",
    "type": "news",
    "severity": "high",
    "title": "Important News - FTI",
    "message": "FTI reports strong Q4 earnings, beats estimates",
    "data": {
      "symbol": "FTI",
      "headline": "FTI reports strong Q4 earnings, beats estimates",
      "summary": "Recent developments suggest positive momentum for FTI with strong market reception.",
      "source": "Yahoo Finance",
      "sentiment": 0.5142729642064997,
      "importance": "high",
      "category": "earnings",
      "publishedAt": "2025-08-03T07:15:21.318Z",
      "url": "https://example.com/news/fti-1754238651571"
    }
  },
  {
    "id": "alert_1754238651572_kgeixxuxq",
    "timestamp": "2025-08-03T16:30:51.572Z",
    "acknowledged": false,
    "symbol": "FTI",
    "type": "news",
    "severity": "high",
    "title": "Important News - FTI",
    "message": "FTI reports strong Q4 earnings, beats estimates",
    "data": {
      "symbol": "FTI",
      "headline": "FTI reports strong Q4 earnings, beats estimates",
      "summary": "Recent developments suggest positive momentum for FTI with strong market reception.",
      "source": "MarketWatch",
      "sentiment": 0.8533156565660497,
      "importance": "high",
      "category": "earnings",
      "publishedAt": "2025-08-03T05:33:15.178Z",
      "url": "https://example.com/news/fti-1754238651572"
    }
  },
  {
    "id": "alert_1754238651776_7af6rd9ti",
    "timestamp": "2025-08-03T16:30:51.776Z",
    "acknowledged": false,
    "symbol": "FTI",
    "type": "insider",
    "severity": "high",
    "title": "Significant Insider BUY - FTI",
    "message": "Jane Doe (CFO) buy 33,608 shares for $14,991,580.697",
    "data": {
      "symbol": "FTI",
      "insider": "Jane Doe",
      "title": "CFO",
      "transactionType": "buy",
      "shares": 33608,
      "price": 446.0717893695801,
      "value": 14991580.697132846,
      "date": "2025-07-29T21:44:30.150Z",
      "filingDate": "2025-08-02T14:46:54.669Z",
      "ownershipPercent": 3.580113911690582
    }
  },
  {
    "id": "alert_1754238651777_0qdo3adtr",
    "timestamp": "2025-08-03T16:30:51.777Z",
    "acknowledged": false,
    "symbol": "FTI",
    "type": "insider",
    "severity": "high",
    "title": "Significant Insider SELL - FTI",
    "message": "John Smith (CEO) sell 41,391 shares for $19,122,074.707",
    "data": {
      "symbol": "FTI",
      "insider": "John Smith",
      "title": "CEO",
      "transactionType": "sell",
      "shares": 41391,
      "price": 461.9862942818125,
      "value": 19122074.7066185,
      "date": "2025-07-27T22:25:06.596Z",
      "filingDate": "2025-08-02T22:12:48.856Z",
      "ownershipPercent": 4.710128612481528
    }
  },
  {
    "id": "alert_1754238651780_mksj29kpa",
    "timestamp": "2025-08-03T16:30:51.780Z",
    "acknowledged": false,
    "symbol": "FTI",
    "type": "analyst",
    "severity": "medium",
    "title": "Analyst UPGRADE - FTI",
    "message": "Wells Fargo upgrades FTI to Sell with $397 target",
    "data": {
      "symbol": "FTI",
      "firm": "Wells Fargo",
      "analyst": "Research Team",
      "action": "upgrade",
      "previousRating": "Sell",
      "newRating": "Sell",
      "previousTarget": 417.988959568222,
      "newTarget": 397.47135318283864,
      "date": "2025-08-01T18:20:45.538Z",
      "reasoning": "Strong earnings momentum"
    }
  },
  {
    "id": "alert_1754238651781_qqc0ju02z",
    "timestamp": "2025-08-03T16:30:51.781Z",
    "acknowledged": false,
    "symbol": "FTI",
    "type": "analyst",
    "severity": "medium",
    "title": "Analyst UPGRADE - FTI",
    "message": "Morgan Stanley upgrades FTI to Underperform with $465 target",
    "data": {
      "symbol": "FTI",
      "firm": "Morgan Stanley",
      "analyst": "Research Team",
      "action": "upgrade",
      "previousRating": "Buy",
      "newRating": "Underperform",
      "previousTarget": 504.5920137233374,
      "newTarget": 464.51597059762025,
      "date": "2025-07-30T07:31:23.030Z",
      "reasoning": "Strong earnings momentum"
    }
  },
  {
    "id": "alert_1754238651987_pvjxuep75",
    "timestamp": "2025-08-03T16:30:51.987Z",
    "acknowledged": false,
    "symbol": "SHG",
    "type": "analyst",
    "severity": "medium",
    "title": "Analyst UPGRADE - SHG",
    "message": "Bank of America upgrades SHG to Outperform with $366 target",
    "data": {
      "symbol": "SHG",
      "firm": "Bank of America",
      "analyst": "Research Team",
      "action": "upgrade",
      "previousRating": "Hold",
      "newRating": "Outperform",
      "previousTarget": 396.34482438645097,
      "newTarget": 366.0955578233963,
      "date": "2025-08-03T01:43:50.841Z",
      "reasoning": "Improved market position"
    }
  },
  {
    "id": "alert_1754238651991_0gu5gmhxu",
    "timestamp": "2025-08-03T16:30:51.991Z",
    "acknowledged": false,
    "symbol": "SHG",
    "type": "insider",
    "severity": "medium",
    "title": "Significant Insider BUY - SHG",
    "message": "Jane Doe (CFO) buy 2,771 shares for $1,281,395.671",
    "data": {
      "symbol": "SHG",
      "insider": "Jane Doe",
      "title": "CFO",
      "transactionType": "buy",
      "shares": 2771,
      "price": 462.4307727052116,
      "value": 1281395.6711661413,
      "date": "2025-08-03T03:30:50.523Z",
      "filingDate": "2025-08-02T23:22:40.377Z",
      "ownershipPercent": 0.10769983807507147
    }
  },
  {
    "id": "alert_1754238651992_6a5xu8g63",
    "timestamp": "2025-08-03T16:30:51.992Z",
    "acknowledged": false,
    "symbol": "SHG",
    "type": "insider",
    "severity": "high",
    "title": "Significant Insider BUY - SHG",
    "message": "Mike Johnson (CTO) buy 11,857 shares for $5,436,212.512",
    "data": {
      "symbol": "SHG",
      "insider": "Mike Johnson",
      "title": "CTO",
      "transactionType": "buy",
      "shares": 11857,
      "price": 458.4812779086059,
      "value": 5436212.51216234,
      "date": "2025-08-03T10:03:58.121Z",
      "filingDate": "2025-07-31T20:53:54.009Z",
      "ownershipPercent": 4.4997371778697435
    }
  },
  {
    "id": "alert_1754238651993_u9j56wutj",
    "timestamp": "2025-08-03T16:30:51.993Z",
    "acknowledged": false,
    "symbol": "SHG",
    "type": "insider",
    "severity": "high",
    "title": "Significant Insider SELL - SHG",
    "message": "Mike Johnson (CTO) sell 18,685 shares for $8,571,763.219",
    "data": {
      "symbol": "SHG",
      "insider": "Mike Johnson",
      "title": "CTO",
      "transactionType": "sell",
      "shares": 18685,
      "price": 458.75104198331314,
      "value": 8571763.219458206,
      "date": "2025-07-29T22:42:02.530Z",
      "filingDate": "2025-08-02T21:30:11.118Z",
      "ownershipPercent": 4.373141744180549
    }
  },
  {
    "id": "alert_1754238651997_5rbga1itm",
    "timestamp": "2025-08-03T16:30:51.997Z",
    "acknowledged": false,
    "symbol": "UBS",
    "type": "news",
    "severity": "high",
    "title": "Important News - UBS",
    "message": "UBS raises full-year guidance",
    "data": {
      "symbol": "UBS",
      "headline": "UBS raises full-year guidance",
      "summary": "Recent developments suggest positive momentum for UBS with strong market reception.",
      "source": "MarketWatch",
      "sentiment": 0.8489805233054813,
      "importance": "high",
      "category": "guidance",
      "publishedAt": "2025-08-03T09:18:01.142Z",
      "url": "https://example.com/news/ubs-1754238651997"
    }
  },
  {
    "id": "alert_1754238651999_woav5umgk",
    "timestamp": "2025-08-03T16:30:51.999Z",
    "acknowledged": false,
    "symbol": "UBS",
    "type": "news",
    "severity": "high",
    "title": "Important News - UBS",
    "message": "UBS raises full-year guidance",
    "data": {
      "symbol": "UBS",
      "headline": "UBS raises full-year guidance",
      "summary": "Recent developments suggest positive momentum for UBS with strong market reception.",
      "source": "Yahoo Finance",
      "sentiment": 0.7879692017139139,
      "importance": "high",
      "category": "guidance",
      "publishedAt": "2025-08-03T14:02:10.982Z",
      "url": "https://example.com/news/ubs-1754238651999"
    }
  },
  {
    "id": "alert_1754238652000_6z7fq7b8k",
    "timestamp": "2025-08-03T16:30:52.000Z",
    "acknowledged": false,
    "symbol": "UBS",
    "type": "news",
    "severity": "high",
    "title": "Important News - UBS",
    "message": "UBS reports strong Q4 earnings, beats estimates",
    "data": {
      "symbol": "UBS",
      "headline": "UBS reports strong Q4 earnings, beats estimates",
      "summary": "Recent developments suggest positive momentum for UBS with strong market reception.",
      "source": "CNBC",
      "sentiment": 0.8273104966248164,
      "importance": "high",
      "category": "earnings",
      "publishedAt": "2025-08-03T13:02:59.301Z",
      "url": "https://example.com/news/ubs-1754238652000"
    }
  },
  {
    "id": "alert_1754238652203_qlqc6y67k",
    "timestamp": "2025-08-03T16:30:52.203Z",
    "acknowledged": false,
    "symbol": "UBS",
    "type": "insider",
    "severity": "high",
    "title": "Significant Insider BUY - UBS",
    "message": "John Smith (CEO) buy 45,151 shares for $20,973,805.543",
    "data": {
      "symbol": "UBS",
      "insider": "John Smith",
      "title": "CEO",
      "transactionType": "buy",
      "shares": 45151,
      "price": 464.52582540054,
      "value": 20973805.542659782,
      "date": "2025-08-03T08:45:05.073Z",
      "filingDate": "2025-08-01T00:57:31.731Z",
      "ownershipPercent": 2.047544537499447
    }
  },
  {
    "id": "alert_1754238652204_wilgflwj3",
    "timestamp": "2025-08-03T16:30:52.204Z",
    "acknowledged": false,
    "symbol": "UBS",
    "type": "insider",
    "severity": "medium",
    "title": "Significant Insider SELL - UBS",
    "message": "Mike Johnson (CTO) sell 9,555 shares for $4,442,330.805",
    "data": {
      "symbol": "UBS",
      "insider": "Mike Johnson",
      "title": "CTO",
      "transactionType": "sell",
      "shares": 9555,
      "price": 464.9221146086773,
      "value": 4442330.805085911,
      "date": "2025-07-31T14:25:34.431Z",
      "filingDate": "2025-08-02T22:58:26.831Z",
      "ownershipPercent": 2.174626769176191
    }
  },
  {
    "id": "alert_1754238652206_nofb9i4up",
    "timestamp": "2025-08-03T16:30:52.206Z",
    "acknowledged": false,
    "symbol": "UBS",
    "type": "insider",
    "severity": "high",
    "title": "Significant Insider BUY - UBS",
    "message": "Jane Doe (CFO) buy 41,201 shares for $19,342,143.439",
    "data": {
      "symbol": "UBS",
      "insider": "Jane Doe",
      "title": "CFO",
      "transactionType": "buy",
      "shares": 41201,
      "price": 469.45810632511456,
      "value": 19342143.438701045,
      "date": "2025-07-29T05:32:43.522Z",
      "filingDate": "2025-08-02T12:19:26.992Z",
      "ownershipPercent": 4.862019106365053
    }
  },
  {
    "id": "alert_1754238652210_svvq3926j",
    "timestamp": "2025-08-03T16:30:52.210Z",
    "acknowledged": false,
    "symbol": "PUK",
    "type": "news",
    "severity": "high",
    "title": "Important News - PUK",
    "message": "PUK raises full-year guidance",
    "data": {
      "symbol": "PUK",
      "headline": "PUK raises full-year guidance",
      "summary": "Recent developments suggest positive momentum for PUK with strong market reception.",
      "source": "Bloomberg",
      "sentiment": 0.8008785061714219,
      "importance": "high",
      "category": "guidance",
      "publishedAt": "2025-08-03T15:20:12.516Z",
      "url": "https://example.com/news/puk-1754238652210"
    }
  },
  {
    "id": "alert_1754238652211_o7x29pkqz",
    "timestamp": "2025-08-03T16:30:52.211Z",
    "acknowledged": false,
    "symbol": "PUK",
    "type": "news",
    "severity": "high",
    "title": "Important News - PUK",
    "message": "PUK reports strong Q4 earnings, beats estimates",
    "data": {
      "symbol": "PUK",
      "headline": "PUK reports strong Q4 earnings, beats estimates",
      "summary": "Recent developments suggest positive momentum for PUK with strong market reception.",
      "source": "Yahoo Finance",
      "sentiment": 0.7500285355156622,
      "importance": "high",
      "category": "earnings",
      "publishedAt": "2025-08-03T07:22:06.598Z",
      "url": "https://example.com/news/puk-1754238652211"
    }
  },
  {
    "id": "alert_1754238652418_qes4qpjx7",
    "timestamp": "2025-08-03T16:30:52.418Z",
    "acknowledged": false,
    "symbol": "PUK",
    "type": "analyst",
    "severity": "medium",
    "title": "Analyst DOWNGRADE - PUK",
    "message": "Goldman Sachs downgrades PUK to Sell with $526 target",
    "data": {
      "symbol": "PUK",
      "firm": "Goldman Sachs",
      "analyst": "Research Team",
      "action": "downgrade",
      "previousRating": "Buy",
      "newRating": "Sell",
      "previousTarget": 512.3389522110367,
      "newTarget": 525.5195911207811,
      "date": "2025-08-03T15:50:39.701Z",
      "reasoning": "Competitive headwinds"
    }
  },
  {
    "id": "alert_1754238652421_sk45bu87c",
    "timestamp": "2025-08-03T16:30:52.421Z",
    "acknowledged": false,
    "symbol": "PUK",
    "type": "insider",
    "severity": "medium",
    "title": "Significant Insider BUY - PUK",
    "message": "Jane Doe (CFO) buy 7,848 shares for $3,590,886.848",
    "data": {
      "symbol": "PUK",
      "insider": "Jane Doe",
      "title": "CFO",
      "transactionType": "buy",
      "shares": 7848,
      "price": 457.5543893387719,
      "value": 3590886.8475306816,
      "date": "2025-07-30T19:16:08.114Z",
      "filingDate": "2025-08-01T03:22:25.558Z",
      "ownershipPercent": 3.044857929141164
    }
  },
  {
    "id": "alert_1754238652422_6lpw6on8k",
    "timestamp": "2025-08-03T16:30:52.422Z",
    "acknowledged": false,
    "symbol": "PUK",
    "type": "insider",
    "severity": "high",
    "title": "Significant Insider BUY - PUK",
    "message": "Sarah Wilson (Director) buy 46,697 shares for $20,886,385.55",
    "data": {
      "symbol": "PUK",
      "insider": "Sarah Wilson",
      "title": "Director",
      "transactionType": "buy",
      "shares": 46697,
      "price": 447.27467609558323,
      "value": 20886385.54963545,
      "date": "2025-07-28T21:15:39.519Z",
      "filingDate": "2025-08-02T03:48:27.234Z",
      "ownershipPercent": 0.910609756020686
    }
  },
  {
    "id": "alert_1754238652629_x00e9roj2",
    "timestamp": "2025-08-03T16:30:52.629Z",
    "acknowledged": false,
    "symbol": "TCBI",
    "type": "analyst",
    "severity": "medium",
    "title": "Analyst UPGRADE - TCBI",
    "message": "Barclays upgrades TCBI to Outperform with $525 target",
    "data": {
      "symbol": "TCBI",
      "firm": "Barclays",
      "analyst": "Research Team",
      "action": "upgrade",
      "previousRating": "Underperform",
      "newRating": "Outperform",
      "previousTarget": 483.16124727479814,
      "newTarget": 524.8399829632723,
      "date": "2025-07-31T07:09:29.931Z",
      "reasoning": "Positive sector outlook"
    }
  },
  {
    "id": "alert_1754238652632_hva252o3k",
    "timestamp": "2025-08-03T16:30:52.632Z",
    "acknowledged": false,
    "symbol": "TCBI",
    "type": "insider",
    "severity": "high",
    "title": "Significant Insider BUY - TCBI",
    "message": "John Smith (CEO) buy 14,206 shares for $6,462,977.518",
    "data": {
      "symbol": "TCBI",
      "insider": "John Smith",
      "title": "CEO",
      "transactionType": "buy",
      "shares": 14206,
      "price": 454.94703068220605,
      "value": 6462977.517871419,
      "date": "2025-08-01T21:37:47.182Z",
      "filingDate": "2025-08-01T15:29:14.375Z",
      "ownershipPercent": 4.59035825878036
    }
  }
]