[
  {
    "symbol": "AMZN",
    "insider": "Sarah Wilson",
    "title": "Director",
    "transactionType": "buy",
    "shares": 35844,
    "price": 170.32004724805145,
    "value": 6104951.773559156,
    "date": "2025-07-30T08:12:13.568Z",
    "filingDate": "2025-07-31T18:09:11.753Z",
    "ownershipPercent": 1.6199031583301848
  },
  {
    "symbol": "AMZN",
    "insider": "John Smith",
    "title": "CEO",
    "transactionType": "buy",
    "shares": 46811,
    "price": 236.154960366281,
    "value": 11054649.84970598,
    "date": "2025-07-30T00:39:38.852Z",
    "filingDate": "2025-08-01T16:55:06.399Z",
    "ownershipPercent": 2.9253983008052784
  },
  {
    "symbol": "AMZN",
    "insider": "Jane Doe",
    "title": "CFO",
    "transactionType": "buy",
    "shares": 40720,
    "price": 212.30123914846308,
    "value": 8644906.458125416,
    "date": "2025-07-28T13:55:14.181Z",
    "filingDate": "2025-08-01T09:53:05.255Z",
    "ownershipPercent": 3.245385823223915
  },
  {
    "symbol": "AMZN",
    "insider": "John Smith",
    "title": "CEO",
    "transactionType": "buy",
    "shares": 44719,
    "price": 214.98815550942322,
    "value": 9614055.326225897,
    "date": "2025-08-02T06:13:52.891Z",
    "filingDate": "2025-07-31T20:56:55.851Z",
    "ownershipPercent": 0.16005929554099066
  },
  {
    "symbol": "AMZN",
    "insider": "John Smith",
    "title": "CEO",
    "transactionType": "buy",
    "shares": 7202,
    "price": 212.43538381143483,
    "value": 1529959.6342099537,
    "date": "2025-07-29T01:53:54.691Z",
    "filingDate": "2025-08-01T12:18:39.371Z",
    "ownershipPercent": 3.8764785946686273
  },
  {
    "symbol": "AMZN",
    "insider": "Sarah Wilson",
    "title": "Director",
    "transactionType": "buy",
    "shares": 3897,
    "price": 213.92448174952898,
    "value": 833663.7053779145,
    "date": "2025-07-30T16:00:09.088Z",
    "filingDate": "2025-08-01T14:32:19.903Z",
    "ownershipPercent": 4.80860999707587
  }
]