[
  {
    "symbol": "HWM",
    "insider": "Jane Doe",
    "title": "CFO",
    "transactionType": "sell",
    "shares": 15929,
    "price": 463.8894799101185,
    "value": 7389295.525488278,
    "date": "2025-07-30T21:06:54.672Z",
    "filingDate": "2025-08-03T11:22:42.026Z",
    "ownershipPercent": 1.1733519111801594
  },
  {
    "symbol": "HWM",
    "insider": "Mike Johnson",
    "title": "CTO",
    "transactionType": "buy",
    "shares": 5138,
    "price": 463.0470809860492,
    "value": 2379135.902106321,
    "date": "2025-08-04T06:01:51.815Z",
    "filingDate": "2025-08-03T05:39:45.999Z",
    "ownershipPercent": 4.519450013319144
  },
  {
    "symbol": "HWM",
    "insider": "Jane Doe",
    "title": "CFO",
    "transactionType": "buy",
    "shares": 20386,
    "price": 447.1476311623472,
    "value": 9115551.60887561,
    "date": "2025-08-02T08:12:10.808Z",
    "filingDate": "2025-08-01T17:13:27.677Z",
    "ownershipPercent": 1.4029496838632227
  }
]