[
  {
    "symbol": "NET",
    "date": "2025-08-03",
    "darkPoolVolume": 1180790,
    "totalVolume": 5317080,
    "darkPoolRatio": 0.22207489825242427,
    "avgDarkPoolSize": 1139,
    "sentiment": "neutral",
    "significantTrades": [
      {
        "size": 72197,
        "price": 455.95050255757576,
        "timestamp": "2025-08-03T10:04:01.763Z"
      },
      {
        "size": 123548,
        "price": 454.69151744662855,
        "timestamp": "2025-08-03T11:14:38.099Z"
      },
      {
        "size": 142120,
        "price": 448.0726187476114,
        "timestamp": "2025-08-03T12:25:03.648Z"
      },
      {
        "size": 101660,
        "price": 453.69691199652493,
        "timestamp": "2025-08-03T10:21:14.393Z"
      },
      {
        "size": 109735,
        "price": 454.1076707110223,
        "timestamp": "2025-08-03T15:41:30.091Z"
      },
      {
        "size": 100717,
        "price": 453.10242760115756,
        "timestamp": "2025-08-03T09:35:10.391Z"
      }
    ]
  },
  {
    "symbol": "NET",
    "date": "2025-08-04",
    "darkPoolVolume": 5864531,
    "totalVolume": 12277897,
    "darkPoolRatio": 0.4776494704264093,
    "avgDarkPoolSize": 3365,
    "sentiment": "bullish",
    "significantTrades": [
      {
        "size": 129382,
        "price": 453.4574363149314,
        "timestamp": "2025-08-04T02:22:30.093Z"
      },
      {
        "size": 89278,
        "price": 453.9405961457358,
        "timestamp": "2025-08-04T01:56:17.722Z"
      },
      {
        "size": 60482,
        "price": 449.7814133210644,
        "timestamp": "2025-08-04T02:36:02.835Z"
      },
      {
        "size": 61388,
        "price": 448.0615248447857,
        "timestamp": "2025-08-04T01:04:22.762Z"
      },
      {
        "size": 61082,
        "price": 454.5445109073606,
        "timestamp": "2025-08-04T07:23:44.553Z"
      }
    ]
  }
]